sosi_call/__init__.py
sosi_call/cli.py
sosi_call/py.typed
sosi_call/render.py
sosi_call-0.1.6.dist-info/WHEEL
sosi_call-0.1.6.dist-info/entry_points.txt
sosi_call-0.1.6.dist-info/METADATA
sosi_call-0.1.6.dist-info/RECORD
