Metadata-Version: 2.3
Name: sosi-call
Version: 0.1.6
Summary: Generate a pixel-art 'call style' avatar video reacting to audio.
Keywords: video,avatar,audio,visualizer,moviepy,librosa
Author: Matías Nicolás Sosa
Author-email: Matías Nicolás Sosa <mnsosa.ms@gmail.com>
License: MIT
Classifier: Programming Language :: Python :: 3
Classifier: License :: OSI Approved :: MIT License
Classifier: Operating System :: OS Independent
Requires-Dist: numpy>=1.24
Requires-Dist: pillow>=10.0
Requires-Dist: moviepy>=1.0.3
Requires-Python: >=3.10
Project-URL: Homepage, https://github.com/mnsosa/sosi-call
Project-URL: Repository, https://github.com/mnsosa/sosi-call
Project-URL: Issues, https://github.com/mnsosa/sosi-call/issues
